wincp/__init__.py
wincp/app.py
wincp/cli.py
wincp/main.py
wincp/utils.py
wincp-1.0.2.dist-info/METADATA
wincp-1.0.2.dist-info/WHEEL
wincp-1.0.2.dist-info/entry_points.txt
wincp-1.0.2.dist-info/top_level.txt
wincp-1.0.2.dist-info/RECORD
