Metadata-Version: 2.4
Name: wincp
Version: 1.0.2
Summary: WinCP - Secure CMP Compressor with GUI and CLI
Author: xqrto
Author-email: Jan <donotreplyonthisemail000@gmail.com>
License: MIT
Requires-Python: >=3.9
Requires-Dist: PySide6
Requires-Dist: cryptography
